{
	"configurations" : 
	[
		{
			"directories" : 
			[
				{
					"build" : ".",
					"childIndexes" : 
					[
						1
					],
					"hasInstallRule" : true,
					"jsonFile" : "directory-.-f5ebdc15457944623624.json",
					"minimumCMakeVersion" : 
					{
						"string" : "3.10"
					},
					"projectIndex" : 0,
					"source" : ".",
					"targetIndexes" : 
					[
						4,
						5
					]
				},
				{
					"build" : "lib/googletest",
					"childIndexes" : 
					[
						2
					],
					"hasInstallRule" : true,
					"jsonFile" : "directory-lib.googletest-f566c6626c443d7d0c98.json",
					"minimumCMakeVersion" : 
					{
						"string" : "3.13"
					},
					"parentIndex" : 0,
					"projectIndex" : 1,
					"source" : "lib/googletest"
				},
				{
					"build" : "lib/googletest/googlemock",
					"childIndexes" : 
					[
						3
					],
					"hasInstallRule" : true,
					"jsonFile" : "directory-lib.googletest.googlemock-5491f09974c7bb15338f.json",
					"minimumCMakeVersion" : 
					{
						"string" : "3.13"
					},
					"parentIndex" : 1,
					"projectIndex" : 2,
					"source" : "lib/googletest/googlemock",
					"targetIndexes" : 
					[
						0,
						1
					]
				},
				{
					"build" : "lib/googletest/googletest",
					"hasInstallRule" : true,
					"jsonFile" : "directory-lib.googletest.googletest-544600c614743a002291.json",
					"minimumCMakeVersion" : 
					{
						"string" : "3.13"
					},
					"parentIndex" : 2,
					"projectIndex" : 3,
					"source" : "lib/googletest/googletest",
					"targetIndexes" : 
					[
						2,
						3
					]
				}
			],
			"name" : "",
			"projects" : 
			[
				{
					"childIndexes" : 
					[
						1
					],
					"directoryIndexes" : 
					[
						0
					],
					"name" : "is_proyecto",
					"targetIndexes" : 
					[
						4,
						5
					]
				},
				{
					"childIndexes" : 
					[
						2
					],
					"directoryIndexes" : 
					[
						1
					],
					"name" : "googletest-distribution",
					"parentIndex" : 0
				},
				{
					"childIndexes" : 
					[
						3
					],
					"directoryIndexes" : 
					[
						2
					],
					"name" : "gmock",
					"parentIndex" : 1,
					"targetIndexes" : 
					[
						0,
						1
					]
				},
				{
					"directoryIndexes" : 
					[
						3
					],
					"name" : "gtest",
					"parentIndex" : 2,
					"targetIndexes" : 
					[
						2,
						3
					]
				}
			],
			"targets" : 
			[
				{
					"directoryIndex" : 2,
					"id" : "gmock::@7712283c01f504ef6d93",
					"jsonFile" : "target-gmock-9e7e84e4a36a2a726977.json",
					"name" : "gmock",
					"projectIndex" : 2
				},
				{
					"directoryIndex" : 2,
					"id" : "gmock_main::@7712283c01f504ef6d93",
					"jsonFile" : "target-gmock_main-42a5366a8e81c02e7d9c.json",
					"name" : "gmock_main",
					"projectIndex" : 2
				},
				{
					"directoryIndex" : 3,
					"id" : "gtest::@7e3677ed2a4dc8c8eb88",
					"jsonFile" : "target-gtest-943005e0db35759d6ff1.json",
					"name" : "gtest",
					"projectIndex" : 3
				},
				{
					"directoryIndex" : 3,
					"id" : "gtest_main::@7e3677ed2a4dc8c8eb88",
					"jsonFile" : "target-gtest_main-4e1a6260da05e699af00.json",
					"name" : "gtest_main",
					"projectIndex" : 3
				},
				{
					"directoryIndex" : 0,
					"id" : "programa.exe::@6890427a1f51a3e7e1df",
					"jsonFile" : "target-programa.exe-fd12ac9bafa746f55367.json",
					"name" : "programa.exe",
					"projectIndex" : 0
				},
				{
					"directoryIndex" : 0,
					"id" : "test_ejecutable.exe::@6890427a1f51a3e7e1df",
					"jsonFile" : "target-test_ejecutable.exe-6df0da6bf4c4b0380de2.json",
					"name" : "test_ejecutable.exe",
					"projectIndex" : 0
				}
			]
		}
	],
	"kind" : "codemodel",
	"paths" : 
	{
		"build" : "/mnt/c/Users/Fran/Documents/GitHub/is_proyecto/build",
		"source" : "/mnt/c/Users/Fran/Documents/GitHub/is_proyecto"
	},
	"version" : 
	{
		"major" : 2,
		"minor" : 3
	}
}
